toolbelt/__init__.py
toolbelt/ignore.py
toolbelt/logging.py
toolbelt/package_resources.py
toolbelt/py.typed
toolbelt/version.py
toolbelt/cli/__init__.py
toolbelt/cli/_utils.py
toolbelt/cli/check.py
toolbelt/cli/config.py
toolbelt/cli/format.py
toolbelt/cli/list.py
toolbelt/cli/main.py
toolbelt/config/__init__.py
toolbelt/config/defaults.py
toolbelt/config/discovery.py
toolbelt/config/file_loaders.py
toolbelt/config/includes.py
toolbelt/config/loader.py
toolbelt/config/models.py
toolbelt/config/parser.py
toolbelt/config/utils.py
toolbelt/resources/presets/README.md
toolbelt/resources/presets/hdw.yaml
toolbelt/resources/presets/python-core.yaml
toolbelt/resources/presets/python-dev.yaml
toolbelt/resources/presets/python-hdw.yaml
toolbelt/resources/presets/python-typed.yaml
toolbelt/resources/presets/recommended.yaml
toolbelt/resources/presets/web.yaml
toolbelt/resources/presets/yaml.yaml
toolbelt/runner/__init__.py
toolbelt/runner/display.py
toolbelt/runner/file_discovery.py
toolbelt/runner/orchestrator.py
toolbelt/runner/tool_execution.py
toolbelt/runner/utils.py
tbelt-0.0.3.dist-info/METADATA
tbelt-0.0.3.dist-info/WHEEL
tbelt-0.0.3.dist-info/entry_points.txt
tbelt-0.0.3.dist-info/licenses/LICENSE
tbelt-0.0.3.dist-info/RECORD
