Metadata-Version: 2.4
Name: tbelt
Version: 0.0.3
Summary: format or run checks on files by running tools on them
Author: hotdog-werx
License-Expression: MIT
License-File: LICENSE
Requires-Python: >=3.11
Requires-Dist: argcomplete<4,>=3.6.2
Requires-Dist: pathspec<1,>=0.12.0
Requires-Dist: pydantic<3,>=2.11.7
Requires-Dist: pyyaml<7,>=6.0
Requires-Dist: rich<15,>=14.0.0
Requires-Dist: structlog<26,>=25.4.0
